setup.py
neurascope/__init__.py
neurascope.egg-info/PKG-INFO
neurascope.egg-info/SOURCES.txt
neurascope.egg-info/dependency_links.txt
neurascope.egg-info/not-zip-safe
neurascope.egg-info/top_level.txt