Metadata-Version: 1.0
Name: neurascope
Version: 0.0.1
Summary: The neural network doctor will see you now
Home-page: http://github.com/rkaplan/neurascope
Author: Russell Kaplan
Author-email: rjkaplan@cs.stanford.edu
License: MIT
Platform: UNKNOWN
